{
  "kind": "collectionType",
  "collectionName": "product_designs",
  "info": {
    "singularName": "product-design",
    "pluralName": "product-designs",
    "displayName": "Product Design",
    "description": ""
  },
  "options": {
    "draftAndPublish": true
  },
  "pluginOptions": {},
  "attributes": {
    "Title": {
      "type": "string"
    },
    "Thumbnail": {
      "type": "media",
      "multiple": false,
      "required": false,
      "allowedTypes": [
        "images",
        "files",
        "videos",
        "audios"
      ]
    },
    "Description": {
      "type": "blocks"
    },
    "product_categories": {
      "type": "relation",
      "relation": "oneToMany",
      "target": "api::product-category.product-category"
    },
    "tags": {
      "type": "relation",
      "relation": "oneToMany",
      "target": "api::tag.tag"
    }
  }
}
